pgawedge/__init__.py
pgawedge/_version.py
pgawedge/alchemy.py
pgawedge/connections.py
pgawedge/data_types.py
pgawedge/ddl.py
pgawedge/dml.py
pgawedge/fixtures.py
pgawedge/functions.py
pgawedge/helpers.py
pgawedge/mixins.py
pgawedge/postgres.py
pgawedge/schema.py
pgawedge/sql.py
pgawedge/triggers.py
pgawedge/views.py
pgawedge-0.2.0.dist-info/METADATA
pgawedge-0.2.0.dist-info/RECORD
pgawedge-0.2.0.dist-info/WHEEL
pgawedge-0.2.0.dist-info/top_level.txt
