Metadata-Version: 2.1
Name: pgawedge
Version: 0.2.0
Summary: sqlalchemy postgresql adapter and utilities.
Home-page: https://github.com/portfoliome/pgawedge
Author: Philip Martin
Author-email: philip.martin@censible.co
License: BSD
Platform: UNKNOWN
Classifier: Intended Audience :: Developers
Classifier: Programming Language :: Python :: 3.6
Classifier: Programming Language :: Python :: 3.7
Classifier: Topic :: Database
Classifier: Topic :: Database :: Database Engines/Servers
Classifier: Topic :: Utilities
Classifier: Development Status :: 4 - Beta
Provides-Extra: develop
Provides-Extra: test
Requires-Dist: postpy
Requires-Dist: psycopg2
Requires-Dist: pytz
Requires-Dist: sqlalchemy
Provides-Extra: develop
Requires-Dist: flake8; extra == 'develop'
Requires-Dist: pylint; extra == 'develop'
Provides-Extra: test
Requires-Dist: pytest-cov; extra == 'test'
Requires-Dist: pytest; extra == 'test'
